ec2cluster
