Metadata-Version: 1.1
Name: ec2cluster
Version: 0.25
Summary: Tools to work with clustered applications (PostgreSQL, Redis) on EC2
Home-page: http://github.com/mikery/ec2cluster
Author: Mike Ryan
Author-email: mike@fadedink.co.uk
License: BSD
Platform: UNKNOWN
Classifier: Development Status :: 4 - Beta
Classifier: Intended Audience :: Developers
Classifier: License :: OSI Approved :: BSD License
Classifier: Natural Language :: English
Classifier: Operating System :: OS Independent
Classifier: Programming Language :: Python
